Week 5/Part 2/CLA_add_1.v
module CLA_add_1(
	input [3:0] a,
	output [3:0] s
);
	 
	wire [3:0] p;
	wire [3:0] c;

	assign	p[0] = !a[0],
			p[1] =  a[1],
			p[2] =  a[2],
			p[3] =  a[3];

	assign	c[0] = 0,
			c[1] = a[0],
			c[2] = a[1] & a[0],
			c[3] = a[2] & a[1] & a[0];

	assign	s = p ^ c;
	
endmodule

Week 5/Part 2/dff_block.v
module dff_block (
	input d, clk, reset,
	output reg q,
	output wire qb
);

	assign qb = ~q;

	always @(posedge clk or posedge reset) begin
		if (reset)
			q <= 0;
		else
			q <= d;
	end

endmodule

Week 5/Part 2/counter.v
`timescale 1ns / 1ps

`include "CLA_add_1.v"
`include "dff_block.v"

module counter(
	input clk,
	input reset,
	output wire [3:0] out
);

	wire [3:0] w1, w2;

	dff_block d1(
		.clk(clk),
		.reset(reset),
		.d(w1[0]),
		.q(out[0]),
		.qb(w2[0])
	);

	dff_block d2(
		.clk(clk),
		.reset(reset),
		.d(w1[1]),
		.q(out[1]),
		.qb(w2[1])
	);

	dff_block d3(
		.clk(clk),
		.reset(reset),
		.d(w1[2]),
		.q(out[2]),
		.qb(w2[2])
	);

	dff_block d4(
		.clk(clk),
		.reset(reset),
		.d(w1[3]),
		.q(out[3]),
		.qb(w2[3])
	);

	CLA_add_1 a1(
		.a(out),
		.s(w1)
	);

endmodule

Week 5/Part 2/counter_tb.v
`timescale 1ns / 1ps
`include "counter.v"

////////////////////////////////////////////////////////////////////////////////
// Company: 
// Engineer:
//
// Create Date:   14:51:27 09/09/2022
// Design Name:   counter
// Module Name:   C:/Users/Student/Desktop/Sem 5 Stuff/Week 5/counter/counter_tb.v
// Project Name:  counter
// Target Device:  
// Tool versions:  
// Description: 
//
// Verilog Test Fixture created by ISE for module: counter
//
// Dependencies:
// 
// Revision:
// Revision 0.01 - File Created
// Additional Comments:
// 
////////////////////////////////////////////////////////////////////////////////

module counter_tb;

	// Inputs
	reg clk;
	reg reset;

	// Outputs
	wire [3:0] out;

	// Instantiate the Unit Under Test (UUT)
	counter uut (
		.clk(clk), 
		.reset(reset), 
		.out(out)
	);

	initial begin
		clk = 1'b0;
		forever #1 clk = ~clk;
	end

	initial begin
			reset = 1'b1;
		#7  reset = 1'b0;
		#23 reset = 1'b1;
		#10 reset = 1'b0;
		#20 reset = 1'b1;
		#10 reset = 1'b0;
	end

	initial begin
		$dumpfile("test.vcd");
		$dumpvars(0, counter_tb);
		$monitor("time=%3d, clk=%d, reset=%d, c=%d", $time, clk, reset, out);

		#120 $finish;
	end

endmodule

Week 5/Part 2/test.vcd
$date
	Tue Sep 13 17:19:44 2022
$end
$version
	Icarus Verilog
$end
$timescale
	1ps
$end
$scope module counter_tb $end
$var wire 4 ! out [3:0] $end
$var reg 1 " clk $end
$var reg 1 # reset $end
$scope module uut $end
$var wire 1 " clk $end
$var wire 1 # reset $end
$var wire 4 $ w2 [3:0] $end
$var wire 4 % w1 [3:0] $end
$var wire 4 & out [3:0] $end
$scope module a1 $end
$var wire 4 ' a [3:0] $end
$var wire 4 ( s [3:0] $end
$var wire 4 ) p [3:0] $end
$var wire 4 * c [3:0] $end
$upscope $end
$scope module d1 $end
$var wire 1 " clk $end
$var wire 1 + d $end
$var wire 1 , qb $end
$var wire 1 # reset $end
$var reg 1 - q $end
$upscope $end
$scope module d2 $end
$var wire 1 " clk $end
$var wire 1 . d $end
$var wire 1 / qb $end
$var wire 1 # reset $end
$var reg 1 0 q $end
$upscope $end
$scope module d3 $end
$var wire 1 " clk $end
$var wire 1 1 d $end
$var wire 1 2 qb $end
$var wire 1 # reset $end
$var reg 1 3 q $end
$upscope $end
$scope module d4 $end
$var wire 1 " clk $end
$var wire 1 4 d $end
$var wire 1 5 qb $end
$var wire 1 # reset $end
$var reg 1 6 q $end
$upscope $end
$upscope $end
$upscope $end
$enddefinitions $end
$comment Show the parameter values. $end
$dumpall
$end
#0
$dumpvars
06
15
04
03
12
01
00
1/
0.
0-
1,
1+
b0 *
b1 )
b1 (
b0 '
b0 &
b1 %
b1111 $
1#
0"
b0 !
$end
#1000
1"
#2000
0"
#3000
1"
#4000
0"
#5000
1"
#6000
0"
#7000
1.
0+
b10 %
b10 (
b1110 $
0,
b0 )
b10 *
b1 !
b1 &
b1 '
1-
1"
0#
#8000
0"
#9000
1+
b11 %
b11 (
0/
b1101 $
1,
b11 )
b0 *
10
b10 !
b10 &
b10 '
0-
1"
#10000
0"
#11000
11
0.
0+
b100 %
b100 (
b1100 $
0,
b10 )
b110 *
b11 !
b11 &
b11 '
1-
1"
#12000
0"
#13000
1+
b101 %
b101 (
02
1/
b1011 $
1,
b101 )
b0 *
13
00
b100 !
b100 &
b100 '
0-
1"
#14000
0"
#15000
1.
0+
b110 %
b110 (
b1010 $
0,
b100 )
b10 *
b101 !
b101 &
b101 '
1-
1"
#16000
0"
#17000
1+
b111 %
b111 (
0/
b1001 $
1,
b111 )
b0 *
10
b110 !
b110 &
b110 '
0-
1"
#18000
0"
#19000
14
01
0.
0+
b1000 %
b1000 (
b1000 $
0,
b110 )
b1110 *
b111 !
b111 &
b111 '
1-
1"
#20000
0"
#21000
1+
b1001 %
b1001 (
05
12
1/
b111 $
1,
b1001 )
b0 *
16
03
00
b1000 !
b1000 &
b1000 '
0-
1"
#22000
0"
#23000
1.
0+
b1010 %
b1010 (
b110 $
0,
b1000 )
b10 *
b1001 !
b1001 &
b1001 '
1-
1"
#24000
0"
#25000
1+
b1011 %
b1011 (
0/
b101 $
1,
b1011 )
b0 *
10
b1010 !
b1010 &
b1010 '
0-
1"
#26000
0"
#27000
11
0.
0+
b1100 %
b1100 (
b100 $
0,
b1010 )
b110 *
b1011 !
b1011 &
b1011 '
1-
1"
#28000
0"
#29000
1+
b1101 %
b1101 (
02
1/
b11 $
1,
b1101 )
b0 *
13
00
b1100 !
b1100 &
b1100 '
0-
1"
#30000
04
01
b1 %
b1 (
12
b1111 $
15
b1 )
03
b0 !
b0 &
b0 '
06
0"
1#
#31000
1"
#32000
0"
#33000
1"
#34000
0"
#35000
1"
#36000
0"
#37000
1"
#38000
0"
#39000
1"
#40000
0"
0#
#41000
1.
0+
b10 %
b10 (
b1110 $
0,
b0 )
b10 *
b1 !
b1 &
b1 '
1-
1"
#42000
0"
#43000
1+
b11 %
b11 (
0/
b1101 $
1,
b11 )
b0 *
10
b10 !
b10 &
b10 '
0-
1"
#44000
0"
#45000
11
0.
0+
b100 %
b100 (
b1100 $
0,
b10 )
b110 *
b11 !
b11 &
b11 '
1-
1"
#46000
0"
#47000
1+
b101 %
b101 (
02
1/
b1011 $
1,
b101 )
b0 *
13
00
b100 !
b100 &
b100 '
0-
1"
#48000
0"
#49000
1.
0+
b110 %
b110 (
b1010 $
0,
b100 )
b10 *
b101 !
b101 &
b101 '
1-
1"
#50000
0"
#51000
1+
b111 %
b111 (
0/
b1001 $
1,
b111 )
b0 *
10
b110 !
b110 &
b110 '
0-
1"
#52000
0"
#53000
14
01
0.
0+
b1000 %
b1000 (
b1000 $
0,
b110 )
b1110 *
b111 !
b111 &
b111 '
1-
1"
#54000
0"
#55000
1+
b1001 %
b1001 (
05
12
1/
b111 $
1,
b1001 )
b0 *
16
03
00
b1000 !
b1000 &
b1000 '
0-
1"
#56000
0"
#57000
1.
0+
b1010 %
b1010 (
b110 $
0,
b1000 )
b10 *
b1001 !
b1001 &
b1001 '
1-
1"
#58000
0"
#59000
1+
b1011 %
b1011 (
0/
b101 $
1,
b1011 )
b0 *
10
b1010 !
b1010 &
b1010 '
0-
1"
#60000
04
0.
b1 %
b1 (
1/
b1111 $
15
b1 )
00
b0 !
b0 &
b0 '
06
0"
1#
#61000
1"
#62000
0"
#63000
1"
#64000
0"
#65000
1"
#66000
0"
#67000
1"
#68000
0"
#69000
1"
#70000
0"
0#
#71000
1.
0+
b10 %
b10 (
b1110 $
0,
b0 )
b10 *
b1 !
b1 &
b1 '
1-
1"
#72000
0"
#73000
1+
b11 %
b11 (
0/
b1101 $
1,
b11 )
b0 *
10
b10 !
b10 &
b10 '
0-
1"
#74000
0"
#75000
11
0.
0+
b100 %
b100 (
b1100 $
0,
b10 )
b110 *
b11 !
b11 &
b11 '
1-
1"
#76000
0"
#77000
1+
b101 %
b101 (
02
1/
b1011 $
1,
b101 )
b0 *
13
00
b100 !
b100 &
b100 '
0-
1"
#78000
0"
#79000
1.
0+
b110 %
b110 (
b1010 $
0,
b100 )
b10 *
b101 !
b101 &
b101 '
1-
1"
#80000
0"
#81000
1+
b111 %
b111 (
0/
b1001 $
1,
b111 )
b0 *
10
b110 !
b110 &
b110 '
0-
1"
#82000
0"
#83000
14
01
0.
0+
b1000 %
b1000 (
b1000 $
0,
b110 )
b1110 *
b111 !
b111 &
b111 '
1-
1"
#84000
0"
#85000
1+
b1001 %
b1001 (
05
12
1/
b111 $
1,
b1001 )
b0 *
16
03
00
b1000 !
b1000 &
b1000 '
0-
1"
#86000
0"
#87000
1.
0+
b1010 %
b1010 (
b110 $
0,
b1000 )
b10 *
b1001 !
b1001 &
b1001 '
1-
1"
#88000
0"
#89000
1+
b1011 %
b1011 (
0/
b101 $
1,
b1011 )
b0 *
10
b1010 !
b1010 &
b1010 '
0-
1"
#90000
0"
#91000
11
0.
0+
b1100 %
b1100 (
b100 $
0,
b1010 )
b110 *
b1011 !
b1011 &
b1011 '
1-
1"
#92000
0"
#93000
1+
b1101 %
b1101 (
02
1/
b11 $
1,
b1101 )
b0 *
13
00
b1100 !
b1100 &
b1100 '
0-
1"
#94000
0"
#95000
1.
0+
b1110 %
b1110 (
b10 $
0,
b1100 )
b10 *
b1101 !
b1101 &
b1101 '
1-
1"
#96000
0"
#97000
1+
b1111 %
b1111 (
0/
b1 $
1,
b1111 )
b0 *
10
b1110 !
b1110 &
b1110 '
0-
1"
#98000
0"
#99000
04
01
0.
0+
b0 %
b0 (
b0 $
0,
b1110 )
b1110 *
b1111 !
b1111 &
b1111 '
1-
1"
#100000
0"
#101000
1+
b1 %
b1 (
15
12
1/
b1111 $
1,
b1 )
b0 *
06
03
00
b0 !
b0 &
b0 '
0-
1"
#102000
0"
#103000
1.
0+
b10 %
b10 (
b1110 $
0,
b0 )
b10 *
b1 !
b1 &
b1 '
1-
1"
#104000
0"
#105000
1+
b11 %
b11 (
0/
b1101 $
1,
b11 )
b0 *
10
b10 !
b10 &
b10 '
0-
1"
#106000
0"
#107000
11
0.
0+
b100 %
b100 (
b1100 $
0,
b10 )
b110 *
b11 !
b11 &
b11 '
1-
1"
#108000
0"
#109000
1+
b101 %
b101 (
02
1/
b1011 $
1,
b101 )
b0 *
13
00
b100 !
b100 &
b100 '
0-
1"
#110000
0"
#111000
1.
0+
b110 %
b110 (
b1010 $
0,
b100 )
b10 *
b101 !
b101 &
b101 '
1-
1"
#112000
0"
#113000
1+
b111 %
b111 (
0/
b1001 $
1,
b111 )
b0 *
10
b110 !
b110 &
b110 '
0-
1"
#114000
0"
#115000
14
01
0.
0+
b1000 %
b1000 (
b1000 $
0,
b110 )
b1110 *
b111 !
b111 &
b111 '
1-
1"
#116000
0"
#117000
1+
b1001 %
b1001 (
05
12
1/
b111 $
1,
b1001 )
b0 *
16
03
00
b1000 !
b1000 &
b1000 '
0-
1"
#118000
0"
#119000
1.
0+
b1010 %
b1010 (
b110 $
0,
b1000 )
b10 *
b1001 !
b1001 &
b1001 '
1-
1"
